pypi_test_first/__init__.py
pypi_test_first-0.1.4.dist-info/METADATA
pypi_test_first-0.1.4.dist-info/WHEEL
pypi_test_first-0.1.4.dist-info/RECORD
