Metadata-Version: 2.4
Name: pypi-test-first
Version: 0.1.4
Summary: A simple test package
Project-URL: Homepage, https://github.com/zs856/pypi-test-first.git
License: MIT
Requires-Python: >=3.13
